sequencefield/__init__.py
sequencefield/constraints.py
sequencefield/fields.py
sequencefield/functions.py
sequencefield/metadata.py
django_sequencefield-1.0.13.dist-info/LICENSE.txt
django_sequencefield-1.0.13.dist-info/METADATA
django_sequencefield-1.0.13.dist-info/WHEEL
django_sequencefield-1.0.13.dist-info/top_level.txt
django_sequencefield-1.0.13.dist-info/RECORD
