Metadata-Version: 2.1
Name: django-sequencefield
Version: 1.0.13
Summary: Additional field from django taking it's value from a postgresql sequence. It is similar to django AutoField, except that multiple model can share ids from a single sequence.  Also add the possibility to generate an id from a sequence AND from the data of another field in the model
Author-email: Loic Quertenmont <loic@deeperanalytics.be>
Maintainer-email: Loic Quertenmont <loic@deeperanalytics.be>
License: MIT License
Project-URL: Homepage, https://github.com/quertenmont/django-sequencefield
Project-URL: Download, https://github.com/quertenmont/django-sequencefield/releases
Project-URL: Documentation, https://github.com/quertenmont/django-sequencefield#readme
Project-URL: Issues, https://github.com/quertenmont/django-sequencefield/issues
Project-URL: Funding, https://github.com/sponsors/quertenmont/
Project-URL: Twitter, https://twitter.com/LoicQuertenmont
Keywords: django,postgresql,sequence,field,autofield,python
Classifier: Development Status :: 5 - Production/Stable
Classifier: Environment :: Web Environment
Classifier: Framework :: Django
Classifier: Framework :: Django :: 5.0
Classifier: Intended Audience :: Developers
Classifier: License :: OSI Approved :: MIT License
Classifier: Natural Language :: English
Classifier: Operating System :: OS Independent
Classifier: Programming Language :: Python :: 3.11
Classifier: Programming Language :: Python :: 3.12
Classifier: Topic :: Software Development :: Build Tools
License-File: LICENSE.txt
